cnn_module/__init__.py
cnn_module/data_utils.py
cnn_module/example.py
cnn_module/model.py
cnn_module/trainer.py
my_cnn_package-0.2.0.dist-info/METADATA
my_cnn_package-0.2.0.dist-info/WHEEL
my_cnn_package-0.2.0.dist-info/top_level.txt
my_cnn_package-0.2.0.dist-info/RECORD
