Metadata-Version: 2.1
Name: my-cnn-package
Version: 0.2.0
Summary: A simple PyTorch CNN package
Author: Cuong Van
Classifier: Programming Language :: Python :: 3
Classifier: License :: OSI Approved :: MIT License
Classifier: Operating System :: OS Independent
Requires-Python: >=3.6
Requires-Dist: torch>=1.10.0
Requires-Dist: torchvision>=0.11.0
